{"D":{"d":{"44":"4.0.4","43":"DROID Razr HD","42":360,"41":0,"40":"4.7","38":312,"37":720,"36":640,"34":1,"33":1280,"32":"2","29":"Motorola","27":1,"23":"XT926","22":"Motorola","10":"Mobile Phone","0":3894838}},"E":{"d":{"44":"1.6","43":"X10 Mini","42":320,"41":0,"40":"2.55","38":157,"37":240,"36":427,"34":0,"33":320,"32":"0.75","29":"Sony Ericsson","27":1,"23":"E10i","22":"Sony Ericsson","10":"Mobile Phone","0":1840682}},"G":{"d":{"29":"Samsung","22":"Samsung"},"c":{"T-":{"c":{"B":{"d":{"44":"3.1","43":"Galaxy Chat","41":0,"40":"3","38":133,"37":240,"34":1,"33":320,"32":"0.75","27":1,"23":"GT-B5330","10":"Mobile Phone","0":3861285}},"I":{"d":{"44":"2.3.6","43":"Galaxy S Advance","42":320,"41":0,"40":"4.3","38":217,"37":480,"36":533,"34":0,"33":800,"32":"1.5","27":1,"23":"GT-I9070","10":"Mobile Phone","0":3299689}},"P":{"d":{"44":"4.0 ","43":"Galaxy Tab 2 7.0","42":600,"41":1,"40":"7","38":170,"37":600,"36":1024,"34":1,"33":1024,"32":"1","27":0,"23":"GT-P3100","10":"Tablet","0":3446948}},"S":{"d":{"41":0,"27":1,"10":"Mobile Phone"},"c":{"5":{"d":{"34":0},"c":{"3":{"d":{"37":240,"33":320,"32":"0.75"},"c":{"0":{"d":{"44":"2.2.2","43":"Galaxy Pocket Duos","40":"2.8","38":143,"23":"GT-S5302","0":4523255}},"6":{"d":{"44":"2.3.5","43":"Galaxy Y","42":320,"40":"3","38":133,"36":427,"23":"GT-S5360","0":2593390}}}},"6":{"d":{"44":"2.2","43":"Galaxy Fit","42":320,"40":"3.92","38":102,"37":240,"36":427,"33":320,"32":"0.75","23":"GT-S5670","0":2415725}},"8":{"d":{"44":"2.1","43":"Galaxy Ace","42":320,"40":"3.5","38":166,"37":320,"36":480,"33":480,"32":"1","23":"GT-S5830i","0":4313856}}}},"6":{"d":{"44":"2.3","43":"Galaxy Y Duos","42":240,"40":"3.14","38":127,"37":240,"36":320,"34":0,"33":320,"32":"0.75","23":"GT-S6102","0":3441738}},"7":{"d":{"44":"2.1","43":"Galaxy S Duos","42":320,"40":"4","38":233,"37":480,"36":533,"34":1,"33":800,"32":"1.5","23":"GT-S7562","0":3979242}}}}}}}},"M":{"d":{"44":"4.0.4","42":213,"41":0,"40":"4","38":144,"37":320,"36":320,"34":0,"33":480,"32":"1.5","29":"Mito","27":1,"23":"A15","22":"Mito","10":"Mobile Phone","0":5340461}},"S":{"d":{"41":0,"27":1,"10":"Mobile Phone"},"c":{"A":{"d":{"34":0,"29":"Samsung"},"c":{"MSUNG-SGH-I":{"c":{"5":{"d":{"44":"2.3.6","43":"Exhilarate","42":320,"40":"4","38":233,"37":480,"36":533,"33":800,"32":"1.5","23":"SGH-I577","22":"AT&T","0":3447297}},"7":{"d":{"22":"Samsung"},"c":{"1":{"d":{"44":"2.3","43":"Galaxy Note","42":400,"40":"5.3","38":285,"37":800,"36":640,"33":1280,"32":"2","23":"SGH-I717","0":3287536}},"2":{"d":{"44":"2.3.3","43":"Galaxy S2 Skyrocket","42":320,"40":"4.51","38":207,"37":480,"36":533,"33":800,"32":"1.5","23":"SGH-I727","0":2685857}}}}}}}},"C":{"d":{"44":"2.3","42":320,"40":"4","38":233,"37":480,"36":533,"34":0,"33":800,"32":"1.5","29":"Samsung","23":"SCH-I405","22":"Samsung","0":2886042}},"Y":{"d":{"44":"4.0.4","42":320,"40":"4.99","38":187,"37":480,"36":533,"34":1,"33":800,"32":"1.5","29":"Symphony","23":"W90","22":"Symphony","0":4646897}}}},"X":{"d":{"45":"Android","44":"1.6","43":"Rachael","42":320,"41":0,"40":"4","38":245,"37":480,"36":569,"34":0,"33":854,"32":"1.5","29":"Sony Ericsson","27":1,"23":"X10i","22":"Sony Ericsson","10":"Mobile Phone","0":1748294}},"Y":{"d":{"44":"4.0.4","43":"ME Tablet Connect 3G","42":1024,"41":1,"40":"6.98","38":170,"37":1024,"36":600,"33":600,"32":"1","29":"HCL","27":0,"23":"Y3","22":"HCL","10":"Tablet","0":4647008}},"Z":{"d":{"44":"2.3.3","43":"Avail","42":320,"41":0,"40":"3.5","38":165,"37":320,"36":480,"34":0,"33":480,"32":"1","29":"ZTE","27":1,"23":"Z990","22":"ZTE","10":"Mobile Phone","0":2922338}}}