{"&":{"d":{"44":"2.3.4","42":320,"41":0,"40":"4.3","38":217,"37":480,"36":533,"34":0,"33":800,"32":"1.5","29":"HTC","27":1,"23":"HD7 (Android)","22":"HTC","10":"Mobile Phone","0":5918371}},"-":{"c":{"7":{"d":{"44":"4.0.4","41":1,"40":"7","38":128,"37":800,"33":400,"27":0,"23":"AT-707","22":"APEX","10":"Tablet","0":3908376}},"A":{"d":{"41":0,"27":1,"10":"Mobile Phone"},"c":{"Q":{"d":{"44":"2.3.5","40":"2.8","38":143,"37":240,"33":320,"23":"AT AQ28D","22":"Wolfgang","0":5820714}},"S":{"c":{"4":{"d":{"32":"1.5"},"c":{"0":{"d":{"44":"2.3.5","42":320,"38":233,"37":480,"36":533,"33":800,"22":"Wolfgang"},"c":{"D":{"d":{"43":"AT-AS40D","40":"4.0","34":1,"29":"Wolfgang","23":"AT-AS40D","0":9047171}},"S":{"d":{"40":"4","34":0,"23":"AT-AS40SE","0":5300113}}}},"3":{"d":{"40":"4.3","36":533,"33":800},"c":{"D":{"c":{" ":{"d":{"44":"2.3.6","42":287,"38":211,"37":430,"34":0,"23":"AT-AS43D","22":"Aldi","0":3903884}},"2":{"d":{"44":"4.0.3","43":"Wolfgang","42":320,"38":217,"37":480,"23":"AT-AS43D2","22":"Aldi","0":3858418}},"3":{"d":{"44":"4.1.2","42":320,"38":217,"37":480,"34":1,"23":"AT-AS43D3","22":"Wolfgang","0":5550639}},"4":{"d":{"44":"4.1.2","42":320,"38":217,"37":480,"34":1,"23":"AT-AS43D4","22":"Wolfgang","0":5795839}}}}}},"5":{"d":{"40":"4.5","38":245,"37":540,"33":960,"22":"Wolfgang"},"c":{"D":{"d":{"44":"4.2.2","42":360,"36":640,"34":0,"23":"AT-AS45D1","0":7449525}},"I":{"d":{"44":"4.1.1","42":360,"36":640,"34":0,"23":"AT-AS45IPS","0":5572166}},"L":{"d":{"44":"4.4.4","42":360,"36":640,"29":"Wolfgang","23":"AT-AS45LTE","0":9976807}},"Q":{"d":{"44":"4.4.2","42":360,"36":640,"29":"Wolfgang"},"c":{" ":{"d":{"43":"AT-AS45Q","34":0,"23":"AT-AS45Q","0":8837413}},"1":{"d":{"23":"AT-AS45Q1","0":7923090}}}},"q":{"d":{"44":"4.2.1"},"c":{"2":{"d":{"42":360,"36":640,"23":"AT-AS45Q2","0":7449498}},"H":{"d":{"42":540,"36":960,"34":1,"29":"Wolfgang","23":"AT-AS45qHD","0":7449470}}}}}}}},"5":{"d":{"22":"Wolfgang"},"c":{"0":{"d":{"40":"5"},"c":{"H":{"d":{"44":"4.2.2","42":360,"38":294,"37":720,"36":640,"33":1280,"32":"2","29":"Wolfgang","23":"AT-AS50HD","0":7391038}},"Q":{"d":{"44":"4.2.1","42":540,"38":220,"37":540,"36":960,"34":1,"33":960,"32":"1.5","23":"AT-AS50Q","0":7529799}},"S":{"d":{"44":"4.2.2","42":1080,"38":441,"37":1080,"36":1920,"34":1,"33":1920,"32":"3","23":"AT-AS50SE","0":7390995}}}},"3":{"d":{"44":"4.1.2","42":360,"40":"5.3","38":208,"37":540,"36":640,"33":960,"32":"1.5","23":"AT-AS53N","0":5549773}},"5":{"d":{"44":"4.4.2","42":360,"40":"5.5","38":267,"37":720,"36":640,"33":1280,"32":"2","29":"Wolfgang","23":"AT-AS55HD1","0":8201772}}}}}}}},"H":{"d":{"41":0,"34":0,"27":1,"23":"Generic Android Mobile","22":"Unknown","10":"Mobile Phone","0":2887676}}}},"1":{"d":{"41":1,"27":0,"10":"Tablet"},"c":{"0":{"d":{"40":"10.1"},"c":{"-":{"d":{"44":"4.2.1","43":"EXCITE","42":1280,"38":149,"37":1280,"36":800,"33":800,"32":"1","29":"Toshiba","23":"AT10-A","22":"Toshiba","0":5572371}},"0":{"d":{"44":"3.1","43":"Thrive","42":1200,"38":149,"37":1280,"36":800,"34":1,"33":800,"32":"1","29":"Toshiba","23":"AT100","22":"Toshiba","0":2558936}},"1":{"d":{"34":0,"32":"1"},"c":{"-":{"d":{"44":"4.4"},"c":[{"d":{"42":1280,"38":149,"37":1280,"36":800,"33":800,"29":"Bauhn","23":"AT101-014","22":"Bauhn","0":10861850}},{"d":{"42":1024,"29":"Onix","23":"AT101-1215","22":"Onix","0":11426060}}]},"T":{"d":{"44":"4.4.2","42":1280,"38":149,"37":1280,"36":800,"33":800,"29":"Bauhn","23":"AT101T-114","22":"Bauhn","0":10478019}}}},"5":{"d":{"44":"3.2","43":"Thrive 10 Tablet","42":1280,"38":149,"37":1280,"36":800,"33":800,"32":"1","29":"Toshiba","23":"AT105","22":"Toshiba","0":3319308}},"L":{"d":{"44":"4.2","43":"Excite","42":1280,"38":299,"37":2560,"36":800,"34":1,"33":1600,"32":"2","29":"Toshiba","23":"AT10LE-A","22":"Toshiba","0":6988622},"m":{"23":1,"0":1,"44":1},"c":{"E-A Build\/JSS15Q) ":{"d":{"44":"4.2.1","23":"AT10LE-A-107","0":6271880}}}},"P":{"d":{"44":"4.2.1","43":"Excite","42":1280,"38":299,"37":2560,"36":800,"33":1600,"32":"2","29":"Toshiba","23":"AT10PE-A","22":"Toshiba","0":5678808}}}},"9":{"d":{"43":"Cinepad","42":1280,"40":"9.7","38":154,"37":1280,"36":768,"34":0,"33":768,"32":"1","29":"Aluratek","23":"AT197F","22":"Aluratek","0":6863640}},"A":{"d":{"44":"4.2","43":"AT1A","40":"7","38":170,"37":1024,"34":0,"33":600,"29":"Evercoss","23":"AT1A","22":"Evercoss","0":8568023}},"C":{"d":{"42":1024,"40":"7","38":170,"37":600,"36":600,"34":0,"33":1024,"32":"1","29":"Evercoss","23":"AT1C","22":"Evercoss","0":6859441}},"D":{"d":{"44":"4.4","43":"Jump S","40":"7","38":133,"37":800,"33":480,"29":"Evercoss","23":"AT1D","22":"Evercoss","0":10889484}},"S":{"d":{"44":"3.2","42":962,"40":"7","38":216,"37":1280,"36":602,"34":1,"33":800,"32":"1.33","29":"Toshiba","23":"AT1S0","22":"Toshiba","0":3414255}}}},"2":{"d":{"44":"3.2","43":"Excite AT200","42":1280,"41":1,"40":"10.1","38":149,"37":1280,"36":800,"34":1,"33":800,"32":"1","29":"Toshiba","27":0,"23":"AT200","22":"Toshiba","10":"Tablet","0":3355236}},"3":{"d":{"41":1,"29":"Toshiba","27":0,"22":"Toshiba","10":"Tablet"},"c":{"0":{"d":{"42":1280,"40":"10.1","38":149,"37":1280,"36":800,"33":800,"32":"1"},"c":[{"c":{" ":{"d":{"44":"4.0.3","34":1,"23":"AT300","0":3760810}},"S":{"d":{"44":"4.1.1","23":"AT300SE","0":5990603}}}}]},"3":{"d":{"44":"4.0.3","43":"Excite 13","40":"13.3","38":138,"37":1600,"33":900,"23":"AT330","0":6007247}}}},"4":{"d":{"44":"4.1.1","43":"Regza Tablet","42":1280,"41":1,"40":"10.1","38":149,"37":1280,"36":800,"34":1,"33":800,"32":"1","29":"Toshiba","27":0,"23":"AT400","22":"Toshiba","10":"Tablet","0":4730929}},"5":{"d":{"41":1,"34":1,"29":"Toshiba","27":0,"22":"Toshiba","10":"Tablet"},"c":{"0":{"d":{"42":1280,"36":800},"c":{"0":{"d":{"44":"4.0.3","43":"Regza","40":"10.06","38":150,"37":800,"33":1280,"23":"AT500","0":4356757}},"3":{"d":{"44":"4.2.1","43":"Regza Tablet","40":"10.1","38":149,"37":1280,"33":800,"32":"1","23":"AT503","0":5884425}}}},"7":{"d":{"44":"4.0.3","43":"Regza","42":962,"40":"7.7","38":196,"37":1280,"36":602,"33":800,"32":"1.33","23":"AT570","0":4523104}}}},"7":{"d":{"41":1,"10":"Tablet"},"c":{"-":{"d":{"42":1024,"40":"7","38":170,"37":1024,"36":600,"34":0,"33":600,"32":"1","29":"Toshiba","27":0,"22":"Toshiba"},"c":{"A":{"d":{"44":"4.2.2","43":"Excite 7c","23":"AT7-A","0":6785994}},"B":{"d":{"44":"4.2.2","43":"Excite 7c","23":"AT7-B","0":6785964}},"C":{"d":{"44":"4.4.2","23":"AT7-C","0":7044312}}}},"0":{"d":{"43":"Regza","40":"10.1","29":"Toshiba","27":0,"22":"Toshiba"},"c":{"0":{"d":{"44":"4.0.3","38":149,"37":1280,"33":800,"23":"AT700","0":13948033}},"3":{"d":{"44":"4.3","38":299,"37":2560,"33":1600,"23":"AT703","0":7617163}}}},"E":{"d":{"44":"4.0.4","42":800,"40":"7","38":133,"37":800,"36":480,"34":0,"33":480,"32":"1","27":0,"23":"AT7E-A13BP","22":"Artview","0":5672145}},"F":{"d":{"44":"5.1","43":"Winner Tab S3","40":"7","38":170,"37":1024,"33":600,"29":"Evercoss","27":1,"23":"AT7F","22":"Evercoss","0":12430992}},"J":{"d":{"44":"4.4","43":"Tab S2 Winner","40":"7","38":169,"37":1024,"33":600,"29":"Evercoss","27":0,"23":"AT7J Plus","22":"Evercoss","0":10935449}}}},"8":{"d":{"44":"4.0.3","43":"Regza Tablet","42":1600,"41":1,"40":"13.3","38":138,"37":1600,"36":900,"34":0,"33":900,"32":"1","29":"Toshiba","27":0,"23":"AT830","22":"Toshiba","10":"Tablet","0":4361599}},"9":{"d":{"44":"4.0.4","41":1,"40":"8","38":117,"37":800,"34":0,"33":480,"27":0,"23":"AT9E-A13WA","22":"Artview","10":"Tablet","0":5639085}},"B":{"d":{"44":"2.3.6","42":320,"41":0,"40":"4.99","38":187,"37":480,"36":533,"34":0,"33":800,"32":"1.5","27":1,"23":"ATB-1108","22":"EKT","10":"Mobile Phone","0":4647024}},"H":{"d":{"42":360,"41":0,"37":1080,"36":640,"33":1920,"32":"3","29":"Huawei","27":1,"22":"Huawei","10":"Mobile Phone"},"c":{"-":{"c":{"A":{"d":{"44":"5.1","43":"Honor 7i","40":"5.2","38":424,"23":"ATH-AL00","0":10594232}},"T":{"d":{"44":"5.1.1","43":"Honor 4A","40":"5","38":441,"23":"ATH-TL00","0":12874255}}}}}},"LAS ":{"c":{"T":{"d":{"44":"4.1.1","41":1,"40":"9.7","38":132,"37":1024,"33":768,"27":0,"23":"TAB R97","22":"Atlas","10":"Tablet","0":4739754}},"W":{"d":{"44":"2.3.5","41":0,"40":"3.51","38":266,"37":480,"33":800,"29":"ZTE","27":1,"23":"Atlas W","22":"ZTE","10":"Mobile Phone","0":4540360}}}},"O":{"d":{"44":"4.0.3","42":1067,"41":1,"38":133,"37":800,"36":640,"34":1,"33":480,"32":"0.75","27":0,"10":"Tablet"},"c":{"7":{"d":{"40":"7.01","23":"ATO7P","22":"VIOS","0":4046634}},"M":{"d":{"40":"7","23":"Atom Pad","22":"Cyrus","0":3886700}}}},"P":{"d":{"44":"2.3.1","42":800,"41":1,"40":"8","38":125,"37":800,"36":600,"33":600,"32":"1","27":0,"23":"Excellent 8","22":"Tomtec","10":"Tablet","0":3291154}}}