{" ":{"d":{"44":"1.5","42":320,"41":0,"40":"3.7","38":252,"37":480,"36":533,"34":0,"33":800,"32":"1.5","27":1,"23":"G2","22":"T-Mobile","10":"Mobile Phone","0":2256853}},"0":{"c":{"1":{"d":{"41":0,"34":0,"29":"Toshiba","27":1,"22":"DoCoMo","10":"Mobile Phone"},"c":{"C":{"d":{"44":"2.1","43":"REGZA Phone T-01C","42":320,"40":"4","38":245,"37":480,"36":569,"33":854,"32":"1.5","23":"T-01C","0":2332986}},"D":{"d":{"44":"2.3.5","43":"REGZA","42":360,"40":"4.29","38":342,"37":720,"36":640,"33":1280,"32":"2","23":"T-01D","0":3283220}}}},"2":{"d":{"44":"4.0.4","43":"REGZA Phone","42":360,"41":0,"40":"4.3","38":256,"37":540,"36":640,"34":1,"33":960,"32":"1.5","29":"Toshiba","27":1,"23":"T-02D","22":"DoCoMo","10":"Mobile Phone","0":3804908}},"7":{"d":{"44":"4.0.4","42":640,"41":1,"40":"7.01","38":133,"37":480,"36":1067,"33":800,"32":"0.75","27":0,"23":"T-07B","22":"Audiosonic","10":"Tablet","0":4505880}}}},"1":{"d":{"41":1,"27":0,"10":"Tablet"},"c":{"0":{"c":{"0":{"d":{"44":"4.1.1","34":0,"32":"1","22":"DGM"},"c":{"5":{"d":{"42":768,"40":"9.7","38":132,"37":768,"36":1024,"33":1024,"23":"T-1005","0":4588638}},"6":{"d":{"42":1024,"40":"10.06","38":118,"37":1024,"36":600,"33":600,"23":"T-1006","0":4632075}}}},"B":{"d":{"44":"4.0.4","40":"10.1","38":118,"37":1024,"33":600,"23":"T-10B","22":"Audiosonic","0":4505894}}}},"1":{"d":{"44":"2.3.3","40":"7.01","38":133,"37":480,"33":800,"23":"T-112","22":"StarPAD","0":4588732}},"3":{"d":{"44":"4.0.4","43":"Shogun 10","42":1200,"40":"10","38":143,"37":1200,"36":800,"34":0,"33":800,"32":"1","23":"Shogun 10","22":"Shiru","0":4575675}},"7":{"d":{"44":"4.1.1","40":"7.01","38":133,"32":"0.75","22":"Audiosonic"},"c":{"B":{"d":{"42":1067,"37":800,"36":640,"34":0,"33":480,"23":"T-17B","0":4633594}},"P":{"d":{"42":640,"37":480,"36":1067,"34":1,"33":800,"23":"T-17P","0":4540567}}}}}},"7":{"d":{"44":"4.4.2","43":"T-704DH","41":1,"40":"7.0","38":170,"37":1024,"34":0,"33":600,"29":"Digimate","27":0,"23":"T-704DH","22":"Digimate","10":"Tablet","0":8822483}},"90":{"c":{" ":{"d":{"44":"4.0.3","42":120,"41":0,"37":240,"36":92,"33":320,"29":"ZTE","27":1,"23":"T90","22":"ZTE","10":"Mobile Phone","0":1716154}},"7":{"d":{"44":"4.0.4","41":1,"40":"9.7","38":132,"37":768,"34":1,"33":1024,"27":0,"23":"T-907","22":"Shenzhen Totsh Industrial","10":"Tablet","0":3935371}},"9":{"d":{"44":"4.0.3","41":1,"40":"9","38":104,"37":800,"33":480,"27":0,"23":"T-909S","22":"DGM","10":"Tablet","0":5913860}}}},"H":{"d":{"44":"2.3.7","42":400,"41":1,"40":"7","38":170,"37":600,"36":683,"34":0,"33":1024,"32":"1.5","27":0,"23":"T-Hub 2","22":"Telstra","10":"Tablet","0":4000975}},"M":{"c":{"7":{"d":{"44":"4.0.3","41":1,"40":"7","38":133,"37":800,"34":0,"33":480,"27":0,"23":"T-M703A","22":"Panle","10":"Tablet","0":5687289}},"o":{"d":{"41":0,"27":1,"22":"T-Mobile","10":"Mobile Phone"},"c":{"bile":{"c":{" ":{"c":{"G":{"d":{"44":"1.5","37":480},"c":{"1":{"d":{"45":"Android","42":315,"40":"3.19","38":181,"36":440,"33":320,"32":"1","23":"G1","0":1096144}},"2":{"d":{"42":320,"40":"3.7","38":252,"36":533,"34":0,"33":800,"32":"1.5","23":"G2","0":2256853}}}},"O":{"d":{"45":"Android","42":240,"40":"2.8","38":107,"37":240,"36":320,"33":320,"23":"Opal","0":1716089}},"V":{"d":{"44":"2.3","42":320,"40":"3.49","38":267,"37":480,"36":533,"34":0,"33":800,"32":"1.5","23":"Vivacity","0":3298609}},"myTouch ":{"c":{"3":{"d":{"37":320,"33":480,"29":"HTC"},"c":{"G":{"c":{" ":{"c":{"B":{"d":{"45":"Android","44":"1.5","43":"myTouch 3G","42":320,"40":"3.2","38":180,"36":480,"34":0,"32":"1","23":"myTouch 3G","0":1942940}},"S":{"d":{"44":"2.1","43":"myTouch 3G Slide","42":213,"40":"3.39","38":170,"36":320,"32":"1.5","23":"myTouch 3G Slide","0":4716815},"m":{"32":1,"23":1,"36":1,"0":1,"42":1,"40":1,"38":1,"43":1,"44":1},"c":{"lide ":{"d":{"45":"Android","34":0},"c":{"Build\/ERE27) ":{"d":{"44":"1.5","43":"myTouch 3G","42":320,"40":"3.2","38":180,"36":480,"32":"1","23":"myTouch 3G","0":1942940}}}}}}}},")":{"d":{"45":"Android","44":"1.5","43":"myTouch 3G","42":320,"40":"3.2","38":180,"36":480,"34":0,"32":"1","23":"myTouch 3G","0":1942940}}}}}},"4":{"d":{"44":"2.2","43":"myTouch 4G","42":320,"40":"3.8","38":246,"37":480,"36":533,"34":0,"33":800,"32":"1.5","29":"HTC","23":"myTouch 4G","0":2259154}},"B":{"d":{"44":"2.3.6","43":"Huawei Phoenix","42":320,"40":"4","38":233,"37":480,"36":533,"34":0,"33":800,"32":"1.5","29":"Huawei","23":"myTouch","0":3920072}},"Q":{"d":{"44":"2.3.6","43":"myTouch Q","42":320,"40":"4","38":233,"37":480,"36":533,"34":0,"33":800,"32":"1.5","29":"Huawei","23":"myTouch Q","0":3920071}},"U":{"d":{"44":"2.3.6","43":"Huawei Phoenix","42":320,"40":"4","38":233,"37":480,"36":533,"34":0,"33":800,"32":"1.5","29":"Huawei","23":"myTouch","0":3920072}}}}}},"_":{"d":{"34":0},"c":{"E":{"d":{"44":"2.1","42":240,"40":"3.8","38":152,"37":320,"36":460,"33":480,"29":"HTC","23":"Espresso","0":1966886}},"G":{"d":{"44":"1.5","42":320,"40":"3.7","38":252,"37":480,"36":533,"33":800,"32":"1.5","23":"G2","0":2256853}},"m":{"d":{"45":"Android","44":"1.5","43":"myTouch 3G","42":320,"40":"3.2","38":180,"37":320,"36":480,"33":480,"32":"1","29":"HTC","23":"myTouch 3G","0":1942940}}}}}}}}}},"s":{"d":{"44":"4.0.4","42":320,"41":0,"40":"4","38":233,"37":480,"36":533,"33":800,"32":"1.5","27":1,"23":"D68X","22":"T-Smart","10":"Mobile Phone","0":5224401}}}