{"3":{"d":{"15":0},"c":{"3":{"d":{"43":"Corby","42":228,"40":"2.63","38":152,"37":240,"36":280,"33":320,"25":"Dolfin","24":1,"23":"GT-S3370","21":1,"20":"Symbian","0":2332663}},"5":{"d":{"42":320,"40":"2.4","38":167,"37":320,"36":320,"34":0,"33":240,"25":"NetFront","24":0,"23":"GT-S3572","21":0,"20":"Samsung proprietary","0":4432363}},"6":{"d":{"43":"Corby","40":"2.8","38":143,"37":240,"33":320,"24":1,"21":0,"20":"Samsung proprietary"},"c":{"5":{"c":{"0":{"d":{"42":228,"36":280,"23":"GT-S3650","0":1659058}},"3":{"d":{"42":240,"36":320,"23":"GT-S3653","0":1830309}}}}}},"8":{"d":{"43":"Corby II","42":228,"40":"3.2","38":125,"37":240,"36":280,"34":0,"33":320,"25":"Dolfin","24":1,"23":"GT-S3850","21":0,"20":"Samsung proprietary","0":2332993}}}},"5":{"d":{"21":0},"c":{"2":{"d":{"42":228,"37":240,"36":360,"34":0,"33":400},"c":{"3":{"d":{"44":"1.0","43":"Star","40":"3","38":155,"24":1,"23":"GT-S5230","20":"Samsung proprietary","15":0,"0":1427754}},"5":{"d":{"44":"1","38":152,"32":"1","25":"Dolfin","24":1,"20":"Bada","15":1},"c":{"0":{"d":{"43":"Wave 2","40":"3.2","23":"GT-S5250","0":2001541}},"3":{"d":{"43":"Wave 525","40":"3.07","23":"GT-S5253","0":2333004}}}},"6":{"d":{"25":"Dolfin","20":"Samsung proprietary","15":0},"c":{"0":{"d":{"43":"Star 2","40":"3.07","38":152,"32":"1","24":1,"23":"GT-S5260","0":2284579}},"3":{"d":{"43":"Star II","40":"3","38":155,"24":0,"23":"GT-S5263","0":2333010}}}}}},"3":{"c":{"3":{"d":{"44":"1","42":228,"38":152,"37":240,"34":0,"25":"Dolfin","24":1,"20":"Bada","15":1},"c":{"0":{"d":{"40":"3.07","36":360,"33":400,"32":"1","23":"GT-S5330","0":2333008}},"3":{"d":{"43":"Wave 533","40":"2.63","36":320,"33":320,"23":"GT-S5333","0":2516858}}}},"5":{"d":{"43":"Shark","42":224,"40":"2.2","38":182,"37":240,"36":280,"33":320,"25":"NetFront","24":0,"23":"GT-S5350","20":"Samsung proprietary","15":0,"0":2396353}},"8":{"d":{"43":"Wave Y","42":320,"40":"3.2","38":180,"37":320,"36":480,"34":1,"33":480,"32":"1","25":"Dolfin","24":1,"20":"Bada","15":1},"c":[{"c":{")":{"d":{"44":"2.0","23":"GT-S5380","0":3479738}},"D":{"d":{"44":"2.0","23":"GT-S5380D","0":3589805}},"K":{"d":{"44":"2","23":"GT-S5380K","0":3352941}}}}]}}},"6":{"d":{"42":228,"40":"3.07","38":152,"37":240,"36":360,"33":400,"25":"Dolfin","24":1,"23":"GT-S5620","20":"Samsung proprietary","15":0,"0":1900393}},"7":{"d":{"34":0,"33":400,"32":"1","25":"Dolfin","24":1,"20":"Bada","15":1},"c":{"5":{"c":{"0":{"d":{"44":"1","42":228,"40":"3.07","38":152,"37":240,"36":360,"23":"GT-S5750E","0":2352401}},"3":{"d":{"44":"1.1","43":"Wave","42":320,"40":"3.2","38":160,"37":320,"36":400,"23":"GT-S5753E","0":2897941}}}}}}}},"7":{"d":{"25":"Dolfin","24":1,"21":0,"20":"Bada","15":1},"c":{"2":{"c":{"3":{"d":{"42":228,"40":"3.07","38":152,"37":240,"36":360,"34":0,"33":400},"c":{"0":{"d":{"44":"1.0","43":"Wave 723","23":"GT-S7230E","0":2352405}},"3":{"d":{"44":"1","32":"1","23":"GT-S7233E","0":2352408}}}},"5":{"d":{"44":"2.0","43":"Wave M","42":320,"40":"3.65","38":158,"37":320,"36":480,"34":1,"33":480,"32":"1","23":"GT-S7250D","0":3642877}}}}}},"8":{"d":{"37":480,"33":800,"25":"Dolfin","24":1,"21":0,"20":"Bada","15":1},"c":{"5":{"d":{"40":"3.06","38":305,"34":0},"c":{"0":{"d":{"44":"1.0","43":"Wave","42":325,"36":518,"23":"GT-S8500","0":1922665}},"3":{"d":{"44":"1.2","43":"Wave 2","42":240,"36":400,"23":"GT-S8530","0":2352410}}}},"6":{"d":{"46":"3.0","44":"2.0","43":"Wave 3","42":320,"40":"4","38":233,"36":533,"34":1,"32":"1.5","23":"GT-S8600","0":2893901}}}}}