{"%":{"d":{"11":1,"9":1,"8":0,"5":0,"2":0,"1":0}},"B":{"d":{"11":1,"9":1,"8":0,"5":0,"2":0,"1":0}},"P":{"d":{"11":1,"9":1,"8":0,"5":0,"2":0,"1":0}},"a":{"d":{"9":0,"8":0,"1":0},"c":{"d":{"d":{"5":0,"3":"Leadify","2":1}},"p":{"d":{"10":"Desktop","5":1,"2":0}}}},"c":{"d":{"11":1,"9":1,"8":0,"5":0,"2":0,"1":0}},"e":{"d":{"9":0,"8":0},"c":{"ch":{"c":{"C":{"d":{"10":"Desktop","5":1,"2":0,"1":0}},"G":{"d":{"5":0,"2":1,"1":1}}}}}},"i":{"d":{"9":0,"8":0,"5":0,"3":"Leikibot","2":1,"1":0}},"m":{"d":{"8":0,"5":0,"1":0},"c":{"o":{"d":{"41":0,"39":0,"35":0,"31":0,"30":0,"29":"Lemon","28":0,"27":1,"22":"Lemon","10":"Mobile Phone","9":1,"2":0},"c":{"n":{"c":{" ":{"d":{"42":240,"40":"2.2","38":182,"37":240,"36":320,"34":0,"33":320,"24":0,"23":"Duo 325","21":0,"19":0,"18":0,"17":0,"16":0,"15":0,"14":0,"13":0,"12":0,"0":2896934}},".":{"d":{"40":"3.3","38":175,"37":320,"33":480,"24":1,"23":"T129","0":6155066}},"_":{"d":{"24":0},"c":{"D":{"d":{"21":0,"19":0,"18":0,"17":0,"16":0,"15":0,"14":0,"13":0,"12":0},"c":{"U":{"d":{"42":240,"40":"2.6","38":154,"37":240,"36":320,"33":320,"23":"Duo 402","0":3647206}},"uo":{"c":{"2":{"d":{"43":"Duo216","42":176,"40":"1.8","38":114,"37":176,"36":208,"33":208,"23":"Duo 216","0":2898209},"m":{"37":1,"23":1,"36":1,"0":1,"42":1,"33":1},"c":{"16 ":{"d":{"42":128,"37":128,"36":160,"33":160,"23":"Duo 216 Plus","0":3648217}}}},"3":{"c":{"0":{"d":{"42":128,"40":"1.8","38":114,"37":128,"36":160,"33":160,"23":"Duo 306","0":3647548}},"2":{"d":{"42":176,"40":"2.2","38":128,"37":176,"36":220,"34":0,"33":220,"23":"Duo 321","0":3647715}},"3":{"d":{"42":240,"40":"2.4","38":167,"37":240,"36":320,"33":320,"23":"Duo 339 Super","0":3648049}},"4":{"d":{"42":176,"40":"2","38":141,"37":176,"36":220,"34":0,"33":220,"23":"Duo 349","0":3647380}}}},"4":{"d":{"42":240,"40":"2.4","38":167,"37":240,"36":320,"33":320,"23":"Duo 405","0":3647881}},"5":{"d":{"42":240,"40":"2.4","38":167,"37":240,"36":320,"33":320,"23":"Duo 525","0":3648382}}}}}},"F":{"d":{"42":176,"40":"2","38":141,"37":176,"36":220,"33":220,"23":"F101","21":0,"19":0,"18":0,"17":0,"16":0,"15":0,"14":0,"13":0,"12":0,"0":3648718}},"S":{"d":{"40":"2.4","38":117,"37":176,"33":220,"23":"S459","0":6068024}},"T":{"d":{"40":"3.7","38":156,"37":320,"33":480,"23":"T109","0":6068048}},"W":{"d":{"42":240,"40":"2","38":200,"37":240,"36":320,"34":0,"33":320,"25":"NetFront","23":"W100","21":0,"19":0,"18":0,"17":0,"16":0,"15":0,"13":0,"12":0,"0":3648550}}}}}}}},"u":{"d":{"9":0,"3":"Lemur","2":1}}}},"n":{"d":{"41":0,"39":0,"35":0,"31":0,"30":0,"29":"Lenovo","28":0,"27":1,"22":"Lenovo","10":"Mobile Phone","9":1,"8":0,"5":0,"2":0,"1":0},"c":{"ovo":{"c":91}}},"o":{"d":{"11":1,"9":1,"8":0,"5":0,"2":0,"1":0}},"p":{"d":{"41":0,"39":0,"35":0,"31":0,"30":0,"28":0,"27":1,"22":"Lephone","10":"Mobile Phone","9":1,"8":0,"5":0,"2":0,"1":0},"c":{"hone_TD":{"c":{"1":{"d":{"40":"2.01","38":140,"37":176,"33":220,"24":1,"23":"TD1128","0":4491097}},"2":{"d":{"40":"2.4","38":167,"37":240,"33":320,"25":"NetFront","24":0,"23":"TD218","21":0,"19":0,"18":0,"17":0,"16":0,"15":0,"14":0,"13":0,"12":0,"0":4313947}},"8":{"d":{"44":"2.3.5","40":"3.5","38":165,"37":320,"33":480,"25":"Android Browser","24":1,"23":"TD8208","21":0,"20":"Android","19":1,"18":0,"17":0,"16":0,"15":0,"14":0,"13":0,"12":0,"0":3989726}}}}}},"s":{"d":{"11":1,"9":1,"8":0,"5":0,"2":0,"1":0}},"t":{"d":{"5":0,"1":0},"c":{"G":{"d":{"11":1,"9":1,"8":0,"2":0}},"s":{"d":{"9":0,"8":1,"2":1}},"t":{"d":{"11":1,"9":1,"8":0,"2":0}}}},"v":{"d":{"9":1,"8":0,"5":0,"2":0,"1":0},"c":{"e":{"d":{"11":1}},"i":{"d":{"41":0,"39":0,"35":0,"32":"1","31":0,"30":0,"28":0,"27":1,"24":0,"16":0,"15":0,"14":0,"13":0,"10":"Mobile Phone"},"c":{"s":{"c":{"-":{"d":{"42":220,"37":220,"36":176,"33":176,"23":"Levi's - the original","22":"ModeLabs","19":0,"18":0,"0":695755}},"_":{"d":{"42":170,"37":176,"36":144,"33":220,"29":"Amoi","25":"NetFront Life","23":"Levis The Original","22":"Amoi","0":1113232}}}}}}}},"x":{"d":{"8":0,"5":0,"1":0},"c":{"a":{"d":{"11":1,"9":1,"2":0}},"i":{"d":{"9":0,"3":"LexiBot","2":1}}}}}